collective.lazysizes-4.1.6-py2.7-nspkg.pth
collective/__pycache__/__init__.cpython-37.pyc
collective/lazysizes/__init__.py
collective/lazysizes/__init__.pyc
collective/lazysizes/config.py
collective/lazysizes/config.pyc
collective/lazysizes/configure.zcml
collective/lazysizes/controlpanel.py
collective/lazysizes/controlpanel.pyc
collective/lazysizes/interfaces.py
collective/lazysizes/interfaces.pyc
collective/lazysizes/logger.py
collective/lazysizes/logger.pyc
collective/lazysizes/profiles.zcml
collective/lazysizes/setuphandlers.py
collective/lazysizes/setuphandlers.pyc
collective/lazysizes/testing.py
collective/lazysizes/testing.pyc
collective/lazysizes/transform.py
collective/lazysizes/transform.pyc
collective/lazysizes/Extensions/Install.py
collective/lazysizes/Extensions/__init__.py
collective/lazysizes/__pycache__/__init__.cpython-37.pyc
collective/lazysizes/__pycache__/config.cpython-37.pyc
collective/lazysizes/__pycache__/controlpanel.cpython-37.pyc
collective/lazysizes/__pycache__/interfaces.cpython-37.pyc
collective/lazysizes/__pycache__/logger.cpython-37.pyc
collective/lazysizes/__pycache__/setuphandlers.cpython-37.pyc
collective/lazysizes/__pycache__/testing.cpython-37.pyc
collective/lazysizes/__pycache__/transform.cpython-37.pyc
collective/lazysizes/browser/__init__.py
collective/lazysizes/browser/__init__.pyc
collective/lazysizes/browser/configure.zcml
collective/lazysizes/browser/__pycache__/__init__.cpython-37.pyc
collective/lazysizes/browser/static/.gitignore
collective/lazysizes/browser/static/README.rst
collective/lazysizes/browser/static/lazysizes-19a41de.js
collective/lazysizes/browser/static/lazysizes-43c36fc.js
collective/lazysizes/browser/static/lazysizes-7d16e01.js
collective/lazysizes/browser/static/lazysizes-d6d7324.js
collective/lazysizes/browser/static/lazysizes-icon.png
collective/lazysizes/browser/static/resources.pt
collective/lazysizes/locales/collective.lazysizes.pot
collective.lazysizes-4.1.6.dist-info/DESCRIPTION.rst
collective.lazysizes-4.1.6.dist-info/METADATA
collective.lazysizes-4.1.6.dist-info/RECORD
collective.lazysizes-4.1.6.dist-info/WHEEL
collective.lazysizes-4.1.6.dist-info/entry_points.txt
collective.lazysizes-4.1.6.dist-info/metadata.json
collective.lazysizes-4.1.6.dist-info/namespace_packages.txt
collective.lazysizes-4.1.6.dist-info/top_level.txt
