Metadata-Version: 2.0
Name: collective.lazysizes
Version: 4.1.6
Summary: Integration of lazysizes, a lightweight lazy loader, into Plone.
Home-page: https://github.com/collective/collective.lazysizes
Author: Hector Velarde
Author-email: hector.velarde@gmail.com
License: UNKNOWN
Platform: UNKNOWN
Classifier: Development Status :: 5 - Production/Stable
Classifier: Environment :: Web Environment
Classifier: Framework :: Plone
Classifier: Framework :: Plone :: 4.3
Classifier: Framework :: Plone :: 5.1
Classifier: Framework :: Plone :: 5.2
Classifier: Intended Audience :: System Administrators
Classifier: License :: OSI Approved :: GNU General Public License v2 (GPLv2)
Classifier: Operating System :: OS Independent
Classifier: Programming Language :: Python
Classifier: Programming Language :: Python :: 2.7
Classifier: Programming Language :: Python :: 3.6
Classifier: Programming Language :: Python :: 3.7
Classifier: Topic :: Software Development :: Libraries :: Python Modules
Provides-Extra: test
Requires-Dist: lxml
Requires-Dist: plone.api
Requires-Dist: plone.app.layout
Requires-Dist: plone.app.registry
Requires-Dist: plone.autoform
Requires-Dist: plone.registry
Requires-Dist: plone.supermodel
Requires-Dist: plone.transformchain
Requires-Dist: Products.CMFPlone (>=4.3)
Requires-Dist: Products.GenericSetup
Requires-Dist: repoze.xmliter
Requires-Dist: setuptools
Requires-Dist: zope.component
Requires-Dist: zope.i18nmessageid
Requires-Dist: zope.interface
Requires-Dist: zope.schema
Provides-Extra: test
Requires-Dist: AccessControl; extra == 'test'
Requires-Dist: plone.app.robotframework; extra == 'test'
Requires-Dist: plone.app.testing[robot]; extra == 'test'
Requires-Dist: plone.browserlayer; extra == 'test'
Requires-Dist: plone.registry; extra == 'test'
Requires-Dist: plone.testing; extra == 'test'
Requires-Dist: robotsuite; extra == 'test'
Requires-Dist: testfixtures; extra == 'test'
Requires-Dist: zope.viewlet; extra == 'test'
